pdf2sb/__init__.py
pdf2sb-0.3.11.dist-info/METADATA
pdf2sb-0.3.11.dist-info/WHEEL
pdf2sb-0.3.11.dist-info/entry_points.txt
pdf2sb-0.3.11.dist-info/licenses/LICENSE
pdf2sb-0.3.11.dist-info/RECORD
