Metadata-Version: 2.3
Name: pdf2sb
Version: 0.3.11
Summary: Upload PDF file to Gyazo as images then convert Scrapbox format
Project-URL: Repository, https://github.com/reiyw/pdf2sb
Author-email: Ryo Takahashi <reiyw.setuve@gmail.com>
License: MIT License
License-File: LICENSE
Requires-Python: ~=3.8
Requires-Dist: click>=8.0
Requires-Dist: pymupdf>=1.24.7
Requires-Dist: python-gyazo>=1.1
